mdformat_admon/__init__.py
mdformat_admon/_helpers.py
mdformat_admon/plugin.py
mdformat_admon/py.typed
mdformat_admon/_synced/__init__.py
mdformat_admon/_synced/admon_factories/README.md
mdformat_admon/_synced/admon_factories/__init__.py
mdformat_admon/_synced/admon_factories/_whitespace_admon_factories.py
mdformat_admon/mdit_plugins/__init__.py
mdformat_admon/mdit_plugins/_python_markdown_admon.py
mdformat_admon-2.1.1.dist-info/entry_points.txt
mdformat_admon-2.1.1.dist-info/licenses/LICENSE
mdformat_admon-2.1.1.dist-info/WHEEL
mdformat_admon-2.1.1.dist-info/METADATA
mdformat_admon-2.1.1.dist-info/RECORD
