Metadata-Version: 2.4
Name: mdformat_admon
Version: 2.1.1
Summary: An mdformat plugin for `admonition`.
Keywords: markdown,markdown-it,mdformat,mdformat_plugin_template
Author-email: kyleking <dev.act.kyle@gmail.com>
Requires-Python: >=3.9.0
Classifier: Intended Audience :: Developers
Classifier: License :: OSI Approved :: MIT License
Classifier: Programming Language :: Python :: 3
Classifier: Topic :: Software Development :: Libraries :: Python Modules
License-File: LICENSE
Requires-Dist: mdformat >= 0.7.19
Requires-Dist: mdit-py-plugins >= 0.4.1
Requires-Dist: pytest >= 8.3.4 ; extra == "test"
Requires-Dist: pytest-beartype >= 0.1.1 ; extra == "test"
Requires-Dist: pytest-cov >= 6.0.0 ; extra == "test"
Project-URL: Bug Tracker, https://github.com/kyleking/mdformat-admon/issues
Project-URL: Changelog, https://github.com/kyleking/mdformat-admon/releases
Project-URL: homepage, https://github.com/kyleking/mdformat-admon
Provides-Extra: test
